[
	{
		"title": "Transport",
		"centerText": "Tesla unveils its first electric truck, to take on commercial haulage vehicles.",
		"linkUrl": "http://www.bbc.co.uk/news/technology-42021713",
		"linkText": "BBC"
	},
	{
		"title": "Pollution",
		"centerText": "Carbon tax thrusts the UK into the top 10 low-carbon electricity world rankings",
		"linkUrl": "http://www.telegraph.co.uk/business/2017/11/15/carbon-tax-thrusts-britain-towards-top-low-carbon-energy-league/",
		"linkText": "Telegraph"
	},
	{
		"title": "Climate Change",
		"centerText": "Worlds biggest investment fund (currently worth about $1 trillion) considers ditching fossil fuels. ",
		"linkUrl": "https://www.theguardian.com/business/2017/nov/16/oil-and-gas-shares-dip-as-norways-central-bank-advises-oslo-to-divest",
		"linkText": "Guardian"
	},
	{
		"title": "Sustainability",
		"centerText": "NASA scientists have estimated that the equivalent of 85 billion tons of CO2 is stored in forests in Congo.",
		"linkUrl": "https://phys.org/news/2017-11-nasa-survey-technique-congo-forest.html",
		"linkText": "NASA"
	},
	{
		"title": "Pollution",
		"centerText": "Dairy farming in New Zealand is polluting lakes and rivers, making up to 60% unswimmable.",
		"linkUrl": "https://www.economist.com/news/asia/21731435-government-data-suggests-60-rivers-and-lakes-are-unswimmable-dairy-farming-polluting-new",
		"linkText": "Economist"
	},
	{
		"title": "Climate Change",
		"centerText": "Butterfly wing inspires photovoltaics: Light absorption can be enhanced by up to 200 percent",
		"linkUrl": "https://sciencebulletin.org/archives/17595.html",
		"linkText": "Science Bulletin"
	},
	{
		"title": "Politics",
		"centerText": "Donald Trump's climate advisor 'doesn't know what key 2-degrees climate target is'",
		"linkUrl": "http://www.independent.co.uk/environment/donald-trump-climate-change-global-warming-george-david-banks-a8054891.html",
		"linkText": "Independant"
	}
]
